basic_algorithm/__init__.py
basic_algorithm/feifei_xia.py
basic_algorithm/from_n_select_m_eq_sum.py
basic_algorithm/n_baoshu_m_leave_left_1.py
basic_algorithm/package_0_1.py
basic_algorithm/quanpailie.py
basic_algorithm/taijie.py
chartered_price_crf/__init__.py
chartered_price_crf/cp.py
datas/__init__.py
lda_demo/__init__.py
lda_demo/gbdt.py
lda_demo/lda_demo.py
lda_demo/tmp.py
lda_demo/data/__init__.py
lda_demo/data_cp/__init__.py
linear_regression/__init__.py
linear_regression/cross_validation_regulation.py
linear_regression/linear_regression.py
nb/__init__.py
nb/naive_bayes.py
word2vec/__init__.py
word2vec/tmp.py
word2vec/word2vec_learn.py
word2vec/data/__init__.py
alibaba_suanfa-1.0.dist-info/METADATA
alibaba_suanfa-1.0.dist-info/WHEEL
alibaba_suanfa-1.0.dist-info/top_level.txt
alibaba_suanfa-1.0.dist-info/RECORD
